il6pred/Data/AAIndexNames.csv
il6pred/Data/Grantham.csv
il6pred/Data/PhysicoChemical.csv
il6pred/Data/Schneider-Wrede.csv
il6pred/Data/aa_attr_group.csv
il6pred/Data/aaind.txt
il6pred/Data/aaindex.csv
il6pred/Data/aaindices.csv
il6pred/Data/atom.csv
il6pred/Data/bin_di.csv
il6pred/Data/bonds.csv
il6pred/Data/data
il6pred/Data/z_aaindex.csv
il6pred/Models/RF_model
il6pred/python_scripts/__init__.py
il6pred/python_scripts/il6.py
il6pred-1.1.dist-info/LICENSE.txt
il6pred-1.1.dist-info/METADATA
il6pred-1.1.dist-info/WHEEL
il6pred-1.1.dist-info/entry_points.txt
il6pred-1.1.dist-info/top_level.txt
il6pred-1.1.dist-info/RECORD
