Metadata-Version: 2.1
Name: il6pred
Version: 1.1
Summary: A method for predicting and designing IL-6 inducing peptides.
Home-page: https://github.com/raghavagps/il6pred
Requires-Python: >=3.7
License-File: LICENSE.txt
Requires-Dist: pandas (==1.1.5)
Requires-Dist: scikit-learn (==0.21.3)
